{
    "1" : {
        "CountryCodes" : "ABW",
        "Country" : "Aruba",
        "Capital" : "Oranjestad",
        "Population" : 71566,
        "LandArea" : 193,
        "Valuta:" : "Aruba Guilder",
        "Language" : "[Dutch, Flemish, Panjabi, Punjabi]",
        "Flag" : "./flagImg/ABW.svg"
    },

    "2" : {
        "CountryCodes" : "AFG",
        "Country" : "Afghanistan",
        "Capital" : "Kabul",
        "Population" : 37172386,
        "LandArea" : 647500,
        "Valuta:" : "Afghanistan Afghani",
        "Language" : "[Pushto, Pashto, Uzbek, Turkmen]",
        "Flag" : "./flagImg/AFG.svg"
    },
    
    "3" : {
        "CountryCodes" : "AGO",
        "Country" : "Angola",
        "Capital" : "Luanda",
        "Population" : 30809762,
        "LandArea" : 1246700,
        "Valuta:" : "Angolan Kwanza",
        "Language" : "[Portuguese]",
        "Flag" : "./flagImg/AGO.svg"
    },

    "4" : {
        "CountryCodes" : "AIA",
        "Country" : "Anguilla",
        "Capital" : "The Valley",
        "Population" : 14731,
        "LandArea" : 91,
        "Valuta:" : "Eastern Caribbean dollar",
        "Language" : "[English]",
        "Flag" : "./flagImg/AIA.svg"
    },
    "5" : {
        "CountryCodes" : "ALA",
        "Country" : "Aland Islands",
        "Capital" : "Mariehamn",
        "Population" : 30129,
        "LandArea" : 1580,
        "Valuta:" : "Eastern Caribbean dollar",
        "Language" : "[Swedish]",
        "Flag" : "./flagImg/ALA.svg"
    },
    "6" : {
        "CountryCodes" : "ALB",
        "Country" : "Albania",
        "Capital" : "Tirana",
        "Population" : 2845955,
        "LandArea" : 28748,
        "Valuta:" : "Lek",
        "Language" : "[Albanian]",
        "Flag" : "./flagImg/ALB.svg"
    },
    "7" : {
        "CountryCodes" : "AND",
        "Country" : "Andorra",
        "Capital" : "Andorra la Vella",
        "Population" : 279535,
        "LandArea" : 468,
        "Valuta:" : "Euro",
        "Language" : "[Catalan]",
        "Flag" : "./flagImg/AND.svg"
    },
    "8" : {
        "CountryCodes" : "ARE",
        "Country" : "United Arab Emirates",
        "Capital" : "Abu Dhabi",
        "Population" : 9282410,
        "LandArea" : 83600,
        "Valuta:" : "UAE dirham",
        "Language" : "[Arabi, English]",
        "Flag" : "./flagImg/ARE.svg"
    },
    "9" : {
        "CountryCodes" : "ARG",
        "Country" : "Argentina",
        "Capital" : "Buenos Aires",
        "Population" : 47327407,
        "LandArea" : 2780400,
        "Valuta:" : "Argentine peso",
        "Language" : "[Spanish]",
        "Flag" : "./flagImg/ARG.svg"
    },
    "10" : {
        "CountryCodes" : "ARM",
        "Country" : "Armenia",
        "Capital" : "Yerevan",
        "Population" : 2963900,
        "LandArea" : 29743,
        "Valuta:" : "Dram",
        "Language" : "[Armenian]",
        "Flag" : "./flagImg/ARM.svg"
    },
    "11" : {
        "CountryCodes" : "ASM",
        "Country" : "American Samoa",
        "Capital" : "Pago Pago",
        "Population" : 463366,
        "LandArea" : 200,
        "Valuta:" : "United States dollar",
        "Language" : "[English, Samoan]",
        "Flag" : "./flagImg/ASM.svg"
    },
    "12" : {
        "CountryCodes" : "ATA",
        "Country" : "Antarctica",
        "Capital" : "Antarctica",
        "Population" : 5000,
        "LandArea" : 14200000,
        "Valuta:" : "United States dollar",
        "Language" : "[English]",
        "Flag" : "./flagImg/ATA.svg"
    },
    "13" : {
        "CountryCodes" : "ATF",
        "Country" : "French Southern Territories",
        "Capital" : "Saint Pierre",
        "Population" : 439666,
        "LandArea" : 400,
        "Valuta:" : "Euro",
        "Language" : "[French]",
        "Flag" : "./flagImg/ATF.svg"
    },
    "14" : {
        "CountryCodes" : "ATG",
        "Country" : "Antigua and Barbuda",
        "Capital" : "St. John's",
        "Population" : 99337,
        "LandArea" : 440,
        "Valuta:" : "East Caribbean dollar",
        "Language" : "[English]",
        "Flag" : "./flagImg/ATG.svg"
    },
    "15" : {
        "CountryCodes" : "AUS",
        "Country" : "Australia",
        "Capital" : "Canberra",
        "Population" : 26002600,
        "LandArea" : 7692024,
        "Valuta:" : "Australian dollar",
        "Language" : "[English]",
        "Flag" : "./flagImg/AUS.svg"
    },
    "16" : {
        "CountryCodes" : "AUT",
        "Country" : "Austria",
        "Capital" : "Vienna",
        "Population" : 9027999,
        "LandArea" : 83879,
        "Valuta:" : "Euro",
        "Language" : "[German]",
        "Flag" : "./flagImg/AUT.svg"
    },
    "17" : {
        "CountryCodes" : "AZE",
        "Country" : "Azerbaijan",
        "Capital" : "Baku",
        "Population" : 10164464,
        "LandArea" : 86600,
        "Valuta:" : "Manat",
        "Language" : "[Azerbaijani]",
        "Flag" : "./flagImg/AZE.svg"
    },
    "18" : {
        "CountryCodes" : "BDI",
        "Country" : "Burundi",
        "Capital" : "Gitega",
        "Population" : 11865821,
        "LandArea" : 27834,
        "Valuta:" : "Burundian franc",
        "Language" : "[Kirundi, French, English]",
        "Flag" : "./flagImg/BDI.svg"
    },
    "19" : {
        "CountryCodes" : "BEL",
        "Country" : "Belgium",
        "Capital" : "Brussels",
        "Population" : 11492641,
        "LandArea" : 30689,
        "Valuta:" : "Euro",
        "Language" : "[Dutch, French, German]",
        "Flag" : "./flagImg/BEL.svg"
    },
    "20" : {
        "CountryCodes" : "BEN",
        "Country" : "Benin",
        "Capital" : "Porto-Novo",
        "Population" : 11733059,
        "LandArea" : 114763,
        "Valuta:" : "West African CFA franc",
        "Language" : "[French]",
        "Flag" : "./flagImg/BEN.svg"
    },
    "21" : {
        "CountryCodes" : "BES",
        "Country" : "Bonaire",
        "Capital" : "Kralendijk",
        "Population" : 20104,
        "LandArea" : 288,
        "Valuta:" : "US dollar",
        "Language" : "[Dutch]",
        "Flag" : "./flagImg/BES.svg"
    },
    "22" : {
        "CountryCodes" : "BFA",
        "Country" : "Burkina Faso",
        "Capital" : "Ouagadougou",
        "Population" : 21510181,
        "LandArea" : 274200,
        "Valuta:" : "West African CFA franc",
        "Language" : "[French]",
        "Flag" : "./flagImg/BFA.svg"
    },
    "23" : {
        "CountryCodes" : "BGD",
        "Country" : "Bangladesh",
        "Capital" : "Dhaka",
        "Population" : 161376708,
        "LandArea" : 148460,
        "Valuta:" : "Taka",
        "Language" : "[Bengali]",
        "Flag" : "./flagImg/BGD.svg"
    },
    "24" : {
        "CountryCodes" : "BGR",
        "Country" : "Bulgaria",
        "Capital" : "Dhaka",
        "Population" : 6863422,
        "LandArea" : 110993,
        "Valuta:" : "Lev",
        "Language" : "[Bulgarian]",
        "Flag" : "./flagImg/BGR.svg"
    },
    "25" : {
        "CountryCodes" : "BHR",
        "Country" : "Bahrain",
        "Capital" : "Manama",
        "Population" : 	1569446,
        "LandArea" : 785,
        "Valuta:" : "Bahraini dinar",
        "Language" : "[Arabic, English]",
        "Flag" : "./flagImg/BHR.svg"
    },
    "26" : {
        "CountryCodes" : "BHS",
        "Country" : "Bahamas",
        "Capital" : "Nassau",
        "Population" : 	400516,
        "LandArea" : 13878,
        "Valuta:" : "Bahamian dollar",
        "Language" : "[English]",
        "Flag" : "./flagImg/BHS.svg"
    }

}